mixnet/__init__.py
mixnet/concrete.net
mixnet/mix.py
mixnet-0.0.3.dist-info/LICENSE
mixnet-0.0.3.dist-info/METADATA
mixnet-0.0.3.dist-info/WHEEL
mixnet-0.0.3.dist-info/top_level.txt
mixnet-0.0.3.dist-info/RECORD
