Metadata-Version: 2.1
Name: mixnet
Version: 0.0.3
Summary: A model to predict compressive strength of concrete based on it's composition
Home-page: https://github.com/DaHamster/mixnet
Author: Has
Author-email: author@example.com
License: UNKNOWN
Project-URL: Bug Tracker, https://github.com/DaHamster/mixnet/issues
Platform: UNKNOWN
Classifier: Programming Language :: Python :: 3
Classifier: License :: OSI Approved :: MIT License
Classifier: Operating System :: OS Independent
Requires-Python: >=3.6
License-File: LICENSE
Requires-Dist: xgboost
Requires-Dist: numpy
